{
    "_comment": "Business Data matching configurations file, Collection name should match with mongo Collection name",
    "bdm": [
        {
            "listener_collections": "samplenews",
            "processed_collections": "samplenewsSubsetCollection",
            "matching_collections": [
                {
                    "stockCollection": "stockCollection"
                }
            ],
            "similarity_measure": "cosine_similarity",
            "similarity_threshold": 0.2,
            "keyword_algorithm": "tf-idf",
            "batch_size": 5
        }
    ]
}